ismlldataset/__init__.py
ismlldataset/__version__.py
ismlldataset/config.py
ismlldataset/utils.py
ismlldataset/zipfiles.py
ismlldataset/zipfiles2.py
ismlldataset/datasets/__init__.py
ismlldataset/datasets/dataset.py
ismlldataset/datasets/functions.py
ismlldataset/datasets/metadataset.py
ismlldataset/tasks/__init__.py
ismlldataset/tasks/functions.py
ismlldataset/tasks/hpo.py
ismlldataset-0.0.3.dist-info/METADATA
ismlldataset-0.0.3.dist-info/WHEEL
ismlldataset-0.0.3.dist-info/top_level.txt
ismlldataset-0.0.3.dist-info/RECORD
