Metadata-Version: 2.1
Name: ismlldataset
Version: 0.0.3
Summary: A Repository for Handling (Meta) Datasets
Home-page: UNKNOWN
Author: Hadi S. Jomaa
Author-email: hsjomaa@ismll.de
License: UNKNOWN
Platform: UNKNOWN
Requires-Python: >=3.6
Requires-Dist: liac-arff (>=2.4.0)
Requires-Dist: xmltodict
Requires-Dist: wget
Requires-Dist: configspace
Requires-Dist: tensorflow
Requires-Dist: tensorflow-probability
Requires-Dist: requests
Requires-Dist: scikit-learn (>=0.18)
Requires-Dist: python-dateutil
Requires-Dist: pandas (>=1.0.0)
Requires-Dist: scipy (>=0.13.3)
Requires-Dist: numpy (>=1.6.2)
